{
  "translation": {
    "id": "BSB",
    "name": "Berean Standard Bible",
    "language": "en",
    "license": "CC0",
    "website": "https://berean.bible"
  },
  "book": {
    "id": "PSA",
    "name": "Psalms",
    "number": 19
  },
  "chapter": {
    "number": 126,
    "content": [
      {
        "type": "verse",
        "number": 2,
        "content": [
          {
            "text": "Then",
            "strong": "H227"
          },
          " ",
          {
            "text": "our mouths",
            "strong": "H6310"
          },
          " ",
          {
            "text": "were filled",
            "strong": "H4390"
          },
          " ",
          {
            "text": "with laughter",
            "strong": "H7814"
          },
          ", ",
          {
            "text": "our tongues",
            "strong": "H3956"
          },
          " ",
          {
            "text": "with shouts of joy",
            "strong": "H7440"
          },
          ". ",
          {
            "text": "Then",
            "strong": "H227"
          },
          " ",
          {
            "text": "it was said",
            "strong": "H559"
          },
          " ",
          {
            "text": "among the nations",
            "strong": "H1471"
          },
          ",\u201c",
          {
            "text": "The LORD",
            "strong": "H3068"
          },
          " ",
          {
            "text": "has done",
            "strong": "H6213"
          },
          " ",
          {
            "text": "great",
            "strong": "H1431"
          },
          " ",
          {
            "text": "things for",
            "strong": "H5973"
          },
          " ",
          {
            "text": "them",
            "strong": "H428"
          },
          ".\u201d"
        ]
      },
      {
        "type": "verse",
        "number": 3,
        "content": [
          {
            "text": "The LORD",
            "strong": "H3068"
          },
          " ",
          {
            "text": "has done",
            "strong": "H6213"
          },
          " ",
          {
            "text": "great",
            "strong": "H1431"
          },
          " ",
          {
            "text": "things for us",
            "strong": "H5973"
          },
          "; ",
          {
            "text": "we are",
            "strong": "H1961"
          },
          " ",
          {
            "text": "filled with joy",
            "strong": "H8056"
          },
          "."
        ]
      },
      {
        "type": "verse",
        "number": 4,
        "content": [
          {
            "text": "Restore",
            "strong": "H7725"
          },
          " ",
          {
            "text": "our captives",
            "strong": "H7622"
          },
          ", ",
          {
            "text": "O LORD",
            "strong": "H3068"
          },
          ", ",
          {
            "text": "-",
            "strong": "H853"
          },
          " ",
          {
            "text": "like streams",
            "strong": "H650"
          },
          " ",
          {
            "text": "in the Negev",
            "strong": "H5045"
          },
          "."
        ]
      },
      {
        "type": "verse",
        "number": 5,
        "content": [
          {
            "text": "Those who sow",
            "strong": "H2232"
          },
          " ",
          {
            "text": "in tears",
            "strong": "H1832"
          },
          " ",
          {
            "text": "will reap",
            "strong": "H7114"
          },
          " ",
          {
            "text": "with shouts of joy",
            "strong": "H7440"
          },
          "."
        ]
      },
      {
        "type": "verse",
        "number": 6,
        "content": [
          {
            "text": "He who goes out",
            "strong": "H1980"
          },
          {
            "text": ". . .",
            "strong": "H1980"
          },
          " ",
          {
            "text": "weeping",
            "strong": "H1058"
          },
          ", ",
          {
            "text": "bearing",
            "strong": "H5375"
          },
          " ",
          {
            "text": "a trail",
            "strong": "H4901"
          },
          " ",
          {
            "text": "of seed",
            "strong": "H2233"
          },
          ", ",
          {
            "text": "will surely return",
            "strong": "H935"
          },
          {
            "text": ". . .",
            "strong": "H935"
          },
          " ",
          {
            "text": "with shouts of joy",
            "strong": "H7440"
          },
          ", ",
          {
            "text": "carrying",
            "strong": "H5375"
          },
          " ",
          {
            "text": "sheaves [of grain]",
            "strong": "H485"
          },
          "."
        ]
      }
    ],
    "footnotes": []
  }
}