{
  "translation": {
    "id": "BSB",
    "name": "Berean Standard Bible",
    "language": "en",
    "license": "CC0",
    "website": "https://berean.bible"
  },
  "book": {
    "id": "MRK",
    "name": "Mark",
    "number": 41
  },
  "chapter": {
    "number": 8,
    "content": [
      {
        "type": "verse",
        "number": 1,
        "content": [
          {
            "text": "In",
            "strong": "G1722"
          },
          " ",
          {
            "text": "those",
            "strong": "G1565"
          },
          " ",
          {
            "text": "-",
            "strong": "G3588"
          },
          " ",
          {
            "text": "days",
            "strong": "G2250"
          },
          " ",
          {
            "text": "[the] crowd",
            "strong": "G3793"
          },
          " ",
          {
            "text": "once again",
            "strong": "G3825"
          },
          " ",
          {
            "text": "became",
            "strong": "G1510"
          },
          " ",
          {
            "text": "very large",
            "strong": "G4183"
          },
          ", ",
          {
            "text": "and",
            "strong": "G2532"
          },
          " ",
          {
            "text": "they had",
            "strong": "G2192"
          },
          " ",
          {
            "text": "nothing",
            "strong": "G3361"
          },
          " ",
          {
            "text": "vvv",
            "strong": "G5101"
          },
          " ",
          {
            "text": "to eat",
            "strong": "G5315"
          },
          ". ",
          {
            "text": "[Jesus] called",
            "strong": "G4341"
          },
          " ",
          {
            "text": "the",
            "strong": "G3588"
          },
          " ",
          {
            "text": "disciples {to Him}",
            "strong": "G3101"
          },
          " ",
          {
            "text": "[and] said",
            "strong": "G3004"
          },
          " ",
          {
            "text": "-",
            "strong": "G846"
          },
          ","
        ]
      },
      {
        "type": "verse",
        "number": 2,
        "content": [
          "\u201c",
          {
            "text": "I have compassion",
            "strong": "G4697"
          },
          " ",
          {
            "text": "for",
            "strong": "G1909"
          },
          " ",
          {
            "text": "[this]",
            "strong": "G3588"
          },
          " ",
          {
            "text": "crowd",
            "strong": "G3793"
          },
          ", ",
          {
            "text": "because",
            "strong": "G3754"
          },
          " ",
          {
            "text": "they have already been",
            "strong": "G4357"
          },
          {
            "text": ". . .",
            "strong": "G2235"
          },
          " ",
          {
            "text": "with Me",
            "strong": "G1473"
          },
          " ",
          {
            "text": "three",
            "strong": "G5140"
          },
          " ",
          {
            "text": "days",
            "strong": "G2250"
          },
          " ",
          {
            "text": "and",
            "strong": "G2532"
          },
          " ",
          {
            "text": "have",
            "strong": "G2192"
          },
          " ",
          {
            "text": "nothing",
            "strong": "G3756"
          },
          " ",
          {
            "text": "vvv",
            "strong": "G5101"
          },
          " ",
          {
            "text": "to eat",
            "strong": "G5315"
          },
          "."
        ]
      },
      {
        "type": "verse",
        "number": 3,
        "content": [
          {
            "text": "-",
            "strong": "G2532"
          },
          " ",
          {
            "text": "If",
            "strong": "G1437"
          },
          " ",
          {
            "text": "I send",
            "strong": "G630"
          },
          " ",
          {
            "text": "them",
            "strong": "G846"
          },
          " ",
          {
            "text": "vvv",
            "strong": "G1519"
          },
          " ",
          {
            "text": "vvv",
            "strong": "G846"
          },
          " ",
          {
            "text": "home",
            "strong": "G3624"
          },
          " ",
          {
            "text": "hungry",
            "strong": "G3523"
          },
          ", ",
          {
            "text": "they will faint",
            "strong": "G1590"
          },
          " ",
          {
            "text": "along",
            "strong": "G1722"
          },
          " ",
          {
            "text": "the",
            "strong": "G3588"
          },
          " ",
          {
            "text": "way",
            "strong": "G3598"
          },
          ". ",
          {
            "text": "For",
            "strong": "G2532"
          },
          " ",
          {
            "text": "some",
            "strong": "G5100"
          },
          " ",
          {
            "text": "of them",
            "strong": "G846"
          },
          " ",
          {
            "text": "have come",
            "strong": "G2240"
          },
          " ",
          {
            "text": "vvv",
            "strong": "G575"
          },
          " ",
          {
            "text": "a great distance",
            "strong": "G3113"
          },
          ".\u201d"
        ]
      },
      {
        "type": "verse",
        "number": 4,
        "content": [
          {
            "text": "-",
            "strong": "G2532"
          },
          " ",
          {
            "text": "His",
            "strong": "G846"
          },
          " ",
          {
            "text": "-",
            "strong": "G3588"
          },
          " ",
          {
            "text": "disciples",
            "strong": "G3101"
          },
          " ",
          {
            "text": "replied",
            "strong": "G611"
          },
          " ",
          {
            "text": "-",
            "strong": "G846"
          },
          " ",
          {
            "text": "-",
            "strong": "G3754"
          },
          ", \u201c",
          {
            "text": "Where",
            "strong": "G4159"
          },
          " ",
          {
            "text": "in",
            "strong": "G1909"
          },
          " ",
          {
            "text": "this desolate place",
            "strong": "G2047"
          },
          {
            "text": ". . .",
            "strong": "G5602"
          },
          " ",
          {
            "text": "could",
            "strong": "G1410"
          },
          " ",
          {
            "text": "anyone",
            "strong": "G5100"
          },
          " ",
          {
            "text": "[find enough] bread",
            "strong": "G740"
          },
          " ",
          {
            "text": "to feed",
            "strong": "G5526"
          },
          " ",
          {
            "text": "all these [people]",
            "strong": "G3778"
          },
          "?\u201d"
        ]
      },
      {
        "type": "verse",
        "number": 5,
        "content": [
          "\u201c",
          {
            "text": "How many",
            "strong": "G4214"
          },
          " ",
          {
            "text": "loaves",
            "strong": "G740"
          },
          " ",
          {
            "text": "do you have",
            "strong": "G2192"
          },
          "?\u201d ",
          {
            "text": "-",
            "strong": "G2532"
          },
          " ",
          {
            "text": "[Jesus] asked",
            "strong": "G2065"
          },
          " ",
          {
            "text": "-",
            "strong": "G846"
          },
          ".\u201c",
          {
            "text": "Seven",
            "strong": "G2033"
          },
          ",\u201d ",
          {
            "text": "-",
            "strong": "G1161"
          },
          " ",
          {
            "text": "-",
            "strong": "G3588"
          },
          " ",
          {
            "text": "they replied",
            "strong": "G2036"
          },
          "."
        ]
      },
      {
        "type": "verse",
        "number": 6,
        "content": [
          {
            "text": "And",
            "strong": "G2532"
          },
          " ",
          {
            "text": "He instructed",
            "strong": "G3853"
          },
          " ",
          {
            "text": "the",
            "strong": "G3588"
          },
          " ",
          {
            "text": "crowd",
            "strong": "G3793"
          },
          " ",
          {
            "text": "to sit down",
            "strong": "G377"
          },
          " ",
          {
            "text": "on",
            "strong": "G1909"
          },
          " ",
          {
            "text": "the",
            "strong": "G3588"
          },
          " ",
          {
            "text": "ground",
            "strong": "G1093"
          },
          ". ",
          {
            "text": "Then",
            "strong": "G2532"
          },
          " ",
          {
            "text": "He took",
            "strong": "G2983"
          },
          " ",
          {
            "text": "the",
            "strong": "G3588"
          },
          " ",
          {
            "text": "seven",
            "strong": "G2033"
          },
          " ",
          {
            "text": "loaves",
            "strong": "G740"
          },
          ", ",
          {
            "text": "gave thanks",
            "strong": "G2168"
          },
          " ",
          {
            "text": "[and] broke [them]",
            "strong": "G2806"
          },
          ", ",
          {
            "text": "and",
            "strong": "G2532"
          },
          " ",
          {
            "text": "gave [them]",
            "strong": "G1325"
          },
          " ",
          {
            "text": "to",
            "strong": "G3588"
          },
          " ",
          {
            "text": "His",
            "strong": "G846"
          },
          " ",
          {
            "text": "disciples",
            "strong": "G3101"
          },
          " ",
          {
            "text": "-",
            "strong": "G2443"
          },
          " ",
          {
            "text": "to set before [the people]",
            "strong": "G3908"
          },
          ". ",
          {
            "text": "And",
            "strong": "G2532"
          },
          " ",
          {
            "text": "they distributed [them]",
            "strong": "G3908"
          },
          " ",
          {
            "text": "to the",
            "strong": "G3588"
          },
          " ",
          {
            "text": "crowd",
            "strong": "G3793"
          },
          "."
        ]
      },
      {
        "type": "verse",
        "number": 7,
        "content": [
          {
            "text": "They also had",
            "strong": "G2192"
          },
          {
            "text": ". . .",
            "strong": "G2532"
          },
          " ",
          {
            "text": "a few",
            "strong": "G3641"
          },
          " ",
          {
            "text": "small fish",
            "strong": "G2485"
          },
          ", ",
          {
            "text": "and",
            "strong": "G2532"
          },
          " ",
          {
            "text": "[Jesus] blessed",
            "strong": "G2127"
          },
          " ",
          {
            "text": "them",
            "strong": "G846"
          },
          " ",
          {
            "text": "[and] ordered that",
            "strong": "G2036"
          },
          " ",
          {
            "text": "these",
            "strong": "G3778"
          },
          " ",
          {
            "text": "be set before [them]",
            "strong": "G3908"
          },
          " ",
          {
            "text": "as well",
            "strong": "G2532"
          },
          "."
        ]
      },
      {
        "type": "verse",
        "number": 8,
        "content": [
          {
            "text": "-",
            "strong": "G2532"
          },
          " ",
          {
            "text": "[The people] ate",
            "strong": "G5315"
          },
          " ",
          {
            "text": "and",
            "strong": "G2532"
          },
          " ",
          {
            "text": "were satisfied",
            "strong": "G5526"
          },
          ", ",
          {
            "text": "and",
            "strong": "G2532"
          },
          " ",
          {
            "text": "[the disciples] picked up",
            "strong": "G142"
          },
          " ",
          {
            "text": "seven",
            "strong": "G2033"
          },
          " ",
          {
            "text": "basketfuls",
            "strong": "G4711"
          },
          " ",
          {
            "text": "of broken pieces",
            "strong": "G2801"
          },
          " ",
          {
            "text": "that were left over",
            "strong": "G4051"
          },
          "."
        ]
      },
      {
        "type": "verse",
        "number": 9,
        "content": [
          {
            "text": "And",
            "strong": "G1161"
          },
          " ",
          {
            "text": "about",
            "strong": "G5613"
          },
          " ",
          {
            "text": "four thousand [men]",
            "strong": "G5070"
          },
          " ",
          {
            "text": "were [ present ]",
            "strong": "G1510"
          },
          ". ",
          {
            "text": "And when",
            "strong": "G2532"
          },
          " ",
          {
            "text": "[Jesus] had dismissed",
            "strong": "G630"
          },
          " ",
          {
            "text": "[the crowd]",
            "strong": "G846"
          },
          ","
        ]
      },
      {
        "type": "verse",
        "number": 10,
        "content": [
          {
            "text": "-",
            "strong": "G2532"
          },
          " ",
          {
            "text": "He immediately",
            "strong": "G2112"
          },
          " ",
          {
            "text": "got",
            "strong": "G1684"
          },
          " ",
          {
            "text": "into",
            "strong": "G1519"
          },
          " ",
          {
            "text": "the",
            "strong": "G3588"
          },
          " ",
          {
            "text": "boat",
            "strong": "G4143"
          },
          " ",
          {
            "text": "with",
            "strong": "G3326"
          },
          " ",
          {
            "text": "His",
            "strong": "G846"
          },
          " ",
          {
            "text": "-",
            "strong": "G3588"
          },
          " ",
          {
            "text": "disciples",
            "strong": "G3101"
          },
          " ",
          {
            "text": "[and] went",
            "strong": "G2064"
          },
          " ",
          {
            "text": "to",
            "strong": "G1519"
          },
          " ",
          {
            "text": "the",
            "strong": "G3588"
          },
          " ",
          {
            "text": "district",
            "strong": "G3313"
          },
          " ",
          {
            "text": "of Dalmanutha",
            "strong": "G1148"
          },
          "."
        ]
      },
      {
        "type": "verse",
        "number": 11,
        "content": [
          {
            "text": "Then",
            "strong": "G2532"
          },
          " ",
          {
            "text": "the",
            "strong": "G3588"
          },
          " ",
          {
            "text": "Pharisees",
            "strong": "G5330"
          },
          " ",
          {
            "text": "came",
            "strong": "G1831"
          },
          " ",
          {
            "text": "and",
            "strong": "G2532"
          },
          " ",
          {
            "text": "began",
            "strong": "G756"
          },
          " ",
          {
            "text": "to argue with",
            "strong": "G4802"
          },
          " ",
          {
            "text": "[Jesus]",
            "strong": "G846"
          },
          ", ",
          {
            "text": "testing",
            "strong": "G3985"
          },
          " ",
          {
            "text": "Him",
            "strong": "G846"
          },
          " ",
          {
            "text": "[by] demanding",
            "strong": "G2212"
          },
          " ",
          {
            "text": "from",
            "strong": "G3844"
          },
          " ",
          {
            "text": "Him",
            "strong": "G846"
          },
          " ",
          {
            "text": "a sign",
            "strong": "G4592"
          },
          " ",
          {
            "text": "from",
            "strong": "G575"
          },
          " ",
          {
            "text": "-",
            "strong": "G3588"
          },
          " ",
          {
            "text": "heaven",
            "strong": "G3772"
          },
          "."
        ]
      },
      {
        "type": "verse",
        "number": 12,
        "content": [
          {
            "text": "-",
            "strong": "G2532"
          },
          " ",
          {
            "text": "[Jesus] sighed deeply",
            "strong": "G389"
          },
          " ",
          {
            "text": "in",
            "strong": "G3588"
          },
          " ",
          {
            "text": "His",
            "strong": "G846"
          },
          " ",
          {
            "text": "spirit",
            "strong": "G4151"
          },
          " ",
          {
            "text": "[and] said",
            "strong": "G3004"
          },
          ", \u201c",
          {
            "text": "Why",
            "strong": "G5101"
          },
          " ",
          {
            "text": "{does] this",
            "strong": "G3778"
          },
          " ",
          {
            "text": "-",
            "strong": "G3588"
          },
          " ",
          {
            "text": "generation",
            "strong": "G1074"
          },
          " ",
          {
            "text": "demand",
            "strong": "G2212"
          },
          " ",
          {
            "text": "a sign",
            "strong": "G4592"
          },
          "? ",
          {
            "text": "Truly",
            "strong": "G281"
          },
          " ",
          {
            "text": "I tell",
            "strong": "G3004"
          },
          " ",
          {
            "text": "you",
            "strong": "G4771"
          },
          ", ",
          {
            "text": "no",
            "strong": "G1487"
          },
          " ",
          {
            "text": "sign",
            "strong": "G4592"
          },
          " ",
          {
            "text": "will be given",
            "strong": "G1325"
          },
          " ",
          {
            "text": "to this",
            "strong": "G3778"
          },
          " ",
          {
            "text": "-",
            "strong": "G3588"
          },
          " ",
          {
            "text": "generation",
            "strong": "G1074"
          },
          ".\u201d"
        ]
      },
      {
        "type": "verse",
        "number": 13,
        "content": [
          {
            "text": "And",
            "strong": "G2532"
          },
          " ",
          {
            "text": "He left",
            "strong": "G863"
          },
          " ",
          {
            "text": "them",
            "strong": "G846"
          },
          ", ",
          {
            "text": "got back into the boat",
            "strong": "G1684"
          },
          {
            "text": ". . .",
            "strong": "G3825"
          },
          ", ",
          {
            "text": "[and] crossed",
            "strong": "G565"
          },
          " ",
          {
            "text": "to",
            "strong": "G1519"
          },
          " ",
          {
            "text": "the",
            "strong": "G3588"
          },
          " ",
          {
            "text": "other side",
            "strong": "G4008"
          },
          "."
        ]
      },
      {
        "type": "verse",
        "number": 14,
        "content": [
          {
            "text": "Now",
            "strong": "G2532"
          },
          " ",
          {
            "text": "[the disciples] had forgotten",
            "strong": "G1950"
          },
          " ",
          {
            "text": "to take",
            "strong": "G2983"
          },
          " ",
          {
            "text": "bread",
            "strong": "G740"
          },
          ", ",
          {
            "text": "-",
            "strong": "G2532"
          },
          " ",
          {
            "text": "except for",
            "strong": "G1487"
          },
          {
            "text": ". . .",
            "strong": "G3361"
          },
          " ",
          {
            "text": "one",
            "strong": "G1520"
          },
          " ",
          {
            "text": "loaf",
            "strong": "G740"
          },
          " ",
          {
            "text": "-",
            "strong": "G3756"
          },
          " ",
          {
            "text": "they had",
            "strong": "G2192"
          },
          " ",
          {
            "text": "with",
            "strong": "G3326"
          },
          " ",
          {
            "text": "them",
            "strong": "G1438"
          },
          " ",
          {
            "text": "in",
            "strong": "G1722"
          },
          " ",
          {
            "text": "the",
            "strong": "G3588"
          },
          " ",
          {
            "text": "boat",
            "strong": "G4143"
          },
          "."
        ]
      },
      {
        "type": "verse",
        "number": 15,
        "content": [
          "\u201c",
          {
            "text": "Watch out",
            "strong": "G3708"
          },
          "!\u201d ",
          {
            "text": "-",
            "strong": "G2532"
          },
          " ",
          {
            "text": "He cautioned",
            "strong": "G1291"
          },
          " ",
          {
            "text": "them",
            "strong": "G846"
          },
          " ",
          {
            "text": "-",
            "strong": "G3004"
          },
          ". \u201c",
          {
            "text": "Beware",
            "strong": "G991"
          },
          " ",
          {
            "text": "of",
            "strong": "G575"
          },
          " ",
          {
            "text": "the",
            "strong": "G3588"
          },
          " ",
          {
            "text": "leaven",
            "strong": "G2219"
          },
          " ",
          {
            "text": "of the",
            "strong": "G3588"
          },
          " ",
          {
            "text": "Pharisees",
            "strong": "G5330"
          },
          " ",
          {
            "text": "and",
            "strong": "G2532"
          },
          " ",
          {
            "text": "-",
            "strong": "G3588"
          },
          " ",
          {
            "text": "-",
            "strong": "G2219"
          },
          " ",
          {
            "text": "of Herod",
            "strong": "G2264"
          },
          ".\u201d"
        ]
      },
      {
        "type": "verse",
        "number": 16,
        "content": [
          {
            "text": "[So]",
            "strong": "G2532"
          },
          " ",
          {
            "text": "they began to discuss",
            "strong": "G1260"
          },
          " ",
          {
            "text": "with",
            "strong": "G4314"
          },
          " ",
          {
            "text": "one another",
            "strong": "G240"
          },
          " ",
          {
            "text": "the fact that",
            "strong": "G3754"
          },
          " ",
          {
            "text": "they had",
            "strong": "G2192"
          },
          " ",
          {
            "text": "no",
            "strong": "G3756"
          },
          " ",
          {
            "text": "bread",
            "strong": "G740"
          },
          "."
        ]
      },
      {
        "type": "verse",
        "number": 17,
        "content": [
          {
            "text": "vvv",
            "strong": "G2532"
          },
          " ",
          {
            "text": "Aware of [their conversation]",
            "strong": "G1097"
          },
          ", ",
          {
            "text": "[Jesus] asked",
            "strong": "G3004"
          },
          " ",
          {
            "text": "them",
            "strong": "G846"
          },
          ", \u201c",
          {
            "text": "Why",
            "strong": "G5101"
          },
          " ",
          {
            "text": "are you debating",
            "strong": "G1260"
          },
          " ",
          {
            "text": "about",
            "strong": "G3754"
          },
          " ",
          {
            "text": "having",
            "strong": "G2192"
          },
          " ",
          {
            "text": "no",
            "strong": "G3756"
          },
          " ",
          {
            "text": "bread",
            "strong": "G740"
          },
          "? ",
          {
            "text": "vvv",
            "strong": "G3768"
          },
          " ",
          {
            "text": "Do you still not see",
            "strong": "G3539"
          },
          " ",
          {
            "text": "or",
            "strong": "G3761"
          },
          " ",
          {
            "text": "understand",
            "strong": "G4920"
          },
          "? ",
          {
            "text": "Do you have",
            "strong": "G2192"
          },
          {
            "text": ". . .",
            "strong": "G4771"
          },
          " ",
          {
            "text": "such hard",
            "strong": "G4456"
          },
          " ",
          {
            "text": "-",
            "strong": "G3588"
          },
          " ",
          {
            "text": "hearts",
            "strong": "G2588"
          },
          "?"
        ]
      },
      {
        "type": "verse",
        "number": 18,
        "content": [
          "\u2018",
          {
            "text": "Having",
            "strong": "G2192"
          },
          " ",
          {
            "text": "eyes",
            "strong": "G3788"
          },
          ", ",
          {
            "text": "vvv",
            "strong": "G3756"
          },
          " ",
          {
            "text": "do you not see",
            "strong": "G991"
          },
          "? ",
          {
            "text": "And",
            "strong": "G2532"
          },
          " ",
          {
            "text": "having",
            "strong": "G2192"
          },
          " ",
          {
            "text": "ears",
            "strong": "G3775"
          },
          ", ",
          {
            "text": "vvv",
            "strong": "G3756"
          },
          " ",
          {
            "text": "do you not hear",
            "strong": "G191"
          },
          "?\u2019 ",
          {
            "text": "And",
            "strong": "G2532"
          },
          " ",
          {
            "text": "vvv",
            "strong": "G3756"
          },
          " ",
          {
            "text": "do you not remember",
            "strong": "G3421"
          },
          "?"
        ]
      },
      {
        "type": "verse",
        "number": 19,
        "content": [
          {
            "text": "When",
            "strong": "G3753"
          },
          " ",
          {
            "text": "I broke",
            "strong": "G2806"
          },
          " ",
          {
            "text": "the",
            "strong": "G3588"
          },
          " ",
          {
            "text": "five",
            "strong": "G4002"
          },
          " ",
          {
            "text": "loaves",
            "strong": "G740"
          },
          " ",
          {
            "text": "for",
            "strong": "G1519"
          },
          " ",
          {
            "text": "the",
            "strong": "G3588"
          },
          " ",
          {
            "text": "five thousand",
            "strong": "G4000"
          },
          ", ",
          {
            "text": "how many",
            "strong": "G4214"
          },
          " ",
          {
            "text": "basketfuls",
            "strong": "G2894"
          },
          {
            "text": ". . .",
            "strong": "G4134"
          },
          " ",
          {
            "text": "of broken pieces",
            "strong": "G2801"
          },
          " ",
          {
            "text": "did you collect",
            "strong": "G142"
          },
          "?\u201d\u201c",
          {
            "text": "Twelve",
            "strong": "G1427"
          },
          ",\u201d ",
          {
            "text": "they answered",
            "strong": "G3004"
          },
          " ",
          {
            "text": "-",
            "strong": "G846"
          },
          "."
        ]
      },
      {
        "type": "verse",
        "number": 20,
        "content": [
          "\u201c",
          {
            "text": "And",
            "strong": "G2532"
          },
          " ",
          {
            "text": "when [I broke]",
            "strong": "G3753"
          },
          " ",
          {
            "text": "the",
            "strong": "G3588"
          },
          " ",
          {
            "text": "seven [loaves]",
            "strong": "G2033"
          },
          " ",
          {
            "text": "for",
            "strong": "G1519"
          },
          " ",
          {
            "text": "the",
            "strong": "G3588"
          },
          " ",
          {
            "text": "four thousand",
            "strong": "G5070"
          },
          ", ",
          {
            "text": "how many",
            "strong": "G4214"
          },
          " ",
          {
            "text": "basketfuls",
            "strong": "G4711"
          },
          {
            "text": ". . .",
            "strong": "G4138"
          },
          " ",
          {
            "text": "of broken pieces",
            "strong": "G2801"
          },
          " ",
          {
            "text": "did you collect",
            "strong": "G142"
          },
          "?\u201d\u201c",
          {
            "text": "Seven",
            "strong": "G2033"
          },
          ",\u201d ",
          {
            "text": "-",
            "strong": "G2532"
          },
          " ",
          {
            "text": "they",
            "strong": "G846"
          },
          " ",
          {
            "text": "said",
            "strong": "G3004"
          },
          "."
        ]
      },
      {
        "type": "verse",
        "number": 21,
        "content": [
          {
            "text": "Then",
            "strong": "G2532"
          },
          " ",
          {
            "text": "He asked",
            "strong": "G2036"
          },
          " ",
          {
            "text": "them",
            "strong": "G846"
          },
          ", \u201c",
          {
            "text": "vvv",
            "strong": "G3768"
          },
          " ",
          {
            "text": "Do you still not understand",
            "strong": "G4920"
          },
          "?\u201d"
        ]
      },
      {
        "type": "verse",
        "number": 22,
        "content": [
          {
            "text": "[When]",
            "strong": "G2532"
          },
          " ",
          {
            "text": "they arrived",
            "strong": "G2064"
          },
          " ",
          {
            "text": "at",
            "strong": "G1519"
          },
          " ",
          {
            "text": "Bethsaida",
            "strong": "G966"
          },
          ", ",
          {
            "text": "-",
            "strong": "G2532"
          },
          " ",
          {
            "text": "[some people] brought",
            "strong": "G5342"
          },
          " ",
          {
            "text": "-",
            "strong": "G846"
          },
          " ",
          {
            "text": "a blind [man]",
            "strong": "G5185"
          },
          " ",
          {
            "text": "and",
            "strong": "G2532"
          },
          " ",
          {
            "text": "begged",
            "strong": "G3870"
          },
          " ",
          {
            "text": "[Jesus]",
            "strong": "G846"
          },
          " ",
          {
            "text": "to",
            "strong": "G2443"
          },
          " ",
          {
            "text": "touch",
            "strong": "G680"
          },
          " ",
          {
            "text": "him",
            "strong": "G846"
          },
          "."
        ]
      },
      {
        "type": "verse",
        "number": 23,
        "content": [
          {
            "text": "So",
            "strong": "G2532"
          },
          " ",
          {
            "text": "He took",
            "strong": "G1949"
          },
          " ",
          {
            "text": "the",
            "strong": "G3588"
          },
          " ",
          {
            "text": "blind [man]",
            "strong": "G5185"
          },
          " ",
          {
            "text": "by the",
            "strong": "G3588"
          },
          " ",
          {
            "text": "hand",
            "strong": "G5495"
          },
          " ",
          {
            "text": "[and] led him",
            "strong": "G1627"
          },
          " ",
          {
            "text": "-",
            "strong": "G846"
          },
          " ",
          {
            "text": "out",
            "strong": "G1854"
          },
          " ",
          {
            "text": "of the",
            "strong": "G3588"
          },
          " ",
          {
            "text": "village",
            "strong": "G2968"
          },
          ". ",
          {
            "text": "Then",
            "strong": "G2532"
          },
          " ",
          {
            "text": "He spit",
            "strong": "G4429"
          },
          " ",
          {
            "text": "on",
            "strong": "G1519"
          },
          " ",
          {
            "text": "[the man\u2019s]",
            "strong": "G846"
          },
          " ",
          {
            "text": "-",
            "strong": "G3588"
          },
          " ",
          {
            "text": "eyes",
            "strong": "G3659"
          },
          " ",
          {
            "text": "[and] placed",
            "strong": "G2007"
          },
          " ",
          {
            "text": "[His]",
            "strong": "G3588"
          },
          " ",
          {
            "text": "hands",
            "strong": "G5495"
          },
          " ",
          {
            "text": "on him",
            "strong": "G846"
          },
          ". \u201c",
          {
            "text": "vvv",
            "strong": "G1487"
          },
          " ",
          {
            "text": "Can you see",
            "strong": "G991"
          },
          " ",
          {
            "text": "anything",
            "strong": "G5100"
          },
          "?\u201d ",
          {
            "text": "He asked",
            "strong": "G1905"
          },
          " ",
          {
            "text": "-",
            "strong": "G846"
          },
          "."
        ]
      },
      {
        "type": "verse",
        "number": 24,
        "content": [
          {
            "text": "-",
            "strong": "G2532"
          },
          " ",
          {
            "text": "[The man] looked up",
            "strong": "G308"
          },
          " ",
          {
            "text": "[and] said",
            "strong": "G2036"
          },
          ", \u201c",
          {
            "text": "I can see",
            "strong": "G991"
          },
          " ",
          {
            "text": "the",
            "strong": "G3588"
          },
          " ",
          {
            "text": "people",
            "strong": "G444"
          },
          ", ",
          {
            "text": "[but]",
            "strong": "G3754"
          },
          " ",
          {
            "text": "they look",
            "strong": "G3708"
          },
          " ",
          {
            "text": "like",
            "strong": "G5613"
          },
          " ",
          {
            "text": "trees",
            "strong": "G1186"
          },
          " ",
          {
            "text": "walking around",
            "strong": "G4043"
          },
          ".\u201d"
        ]
      },
      {
        "type": "verse",
        "number": 25,
        "content": [
          {
            "text": "Once again",
            "strong": "G1534"
          },
          {
            "text": ". . .",
            "strong": "G3825"
          },
          " ",
          {
            "text": "[Jesus] placed",
            "strong": "G2007"
          },
          " ",
          {
            "text": "[His]",
            "strong": "G3588"
          },
          " ",
          {
            "text": "hands",
            "strong": "G5495"
          },
          " ",
          {
            "text": "on",
            "strong": "G1909"
          },
          " ",
          {
            "text": "[the man\u2019s]",
            "strong": "G846"
          },
          " ",
          {
            "text": "-",
            "strong": "G3588"
          },
          " ",
          {
            "text": "eyes",
            "strong": "G3788"
          },
          ", ",
          {
            "text": "and when",
            "strong": "G2532"
          },
          " ",
          {
            "text": "he opened them",
            "strong": "G1227"
          },
          " ",
          {
            "text": "-",
            "strong": "G2532"
          },
          " ",
          {
            "text": "[his sight] was restored",
            "strong": "G600"
          },
          ", ",
          {
            "text": "and",
            "strong": "G2532"
          },
          " ",
          {
            "text": "he could see",
            "strong": "G1689"
          },
          " ",
          {
            "text": "everything",
            "strong": "G537"
          },
          " ",
          {
            "text": "clearly",
            "strong": "G5081"
          },
          "."
        ]
      },
      {
        "type": "verse",
        "number": 26,
        "content": [
          {
            "text": "-",
            "strong": "G2532"
          },
          " ",
          {
            "text": "[Jesus] sent",
            "strong": "G649"
          },
          " ",
          {
            "text": "him",
            "strong": "G846"
          },
          " ",
          {
            "text": "vvv",
            "strong": "G1519"
          },
          " ",
          {
            "text": "vvv",
            "strong": "G846"
          },
          " ",
          {
            "text": "home",
            "strong": "G3624"
          },
          " ",
          {
            "text": "[and] said",
            "strong": "G3004"
          },
          ", \u201c",
          {
            "text": "vvv",
            "strong": "G3366"
          },
          " ",
          {
            "text": "Do not go back",
            "strong": "G1525"
          },
          " ",
          {
            "text": "into",
            "strong": "G1519"
          },
          " ",
          {
            "text": "the",
            "strong": "G3588"
          },
          " ",
          {
            "text": "village",
            "strong": "G2968"
          },
          ".\u201d"
        ]
      },
      {
        "type": "verse",
        "number": 27,
        "content": [
          {
            "text": "Then",
            "strong": "G2532"
          },
          " ",
          {
            "text": "-",
            "strong": "G3588"
          },
          " ",
          {
            "text": "Jesus",
            "strong": "G2424"
          },
          " ",
          {
            "text": "and",
            "strong": "G2532"
          },
          " ",
          {
            "text": "His",
            "strong": "G846"
          },
          " ",
          {
            "text": "-",
            "strong": "G3588"
          },
          " ",
          {
            "text": "disciples",
            "strong": "G3101"
          },
          " ",
          {
            "text": "went on",
            "strong": "G1831"
          },
          " ",
          {
            "text": "to",
            "strong": "G1519"
          },
          " ",
          {
            "text": "the",
            "strong": "G3588"
          },
          " ",
          {
            "text": "villages",
            "strong": "G2968"
          },
          " ",
          {
            "text": "around Caesarea",
            "strong": "G2542"
          },
          " ",
          {
            "text": "-",
            "strong": "G3588"
          },
          " ",
          {
            "text": "Philippi",
            "strong": "G5376"
          },
          ". ",
          {
            "text": "-",
            "strong": "G2532"
          },
          " ",
          {
            "text": "On",
            "strong": "G1722"
          },
          " ",
          {
            "text": "the",
            "strong": "G3588"
          },
          " ",
          {
            "text": "way",
            "strong": "G3598"
          },
          ", ",
          {
            "text": "He questioned",
            "strong": "G1905"
          },
          " ",
          {
            "text": "His",
            "strong": "G846"
          },
          " ",
          {
            "text": "-",
            "strong": "G3588"
          },
          " ",
          {
            "text": "disciples",
            "strong": "G3101"
          },
          " ",
          {
            "text": "-",
            "strong": "G3004"
          },
          " ",
          {
            "text": "-",
            "strong": "G846"
          },
          ": \u201c",
          {
            "text": "Who",
            "strong": "G5101"
          },
          " ",
          {
            "text": "-",
            "strong": "G3588"
          },
          " ",
          {
            "text": "{do} people",
            "strong": "G444"
          },
          " ",
          {
            "text": "say",
            "strong": "G3004"
          },
          " ",
          {
            "text": "I",
            "strong": "G1473"
          },
          " ",
          {
            "text": "am",
            "strong": "G1510"
          },
          "?\u201d"
        ]
      },
      {
        "type": "verse",
        "number": 28,
        "content": [
          {
            "text": "They replied",
            "strong": "G2036"
          },
          {
            "text": ". . .",
            "strong": "G846"
          },
          {
            "text": ". . .",
            "strong": "G3004"
          },
          " ",
          {
            "text": "-",
            "strong": "G3754"
          },
          ", \u201c",
          {
            "text": "[Some say] John",
            "strong": "G2491"
          },
          " ",
          {
            "text": "the",
            "strong": "G3588"
          },
          " ",
          {
            "text": "Baptist",
            "strong": "G910"
          },
          "; ",
          {
            "text": "-",
            "strong": "G1161"
          },
          " ",
          {
            "text": "-",
            "strong": "G3588"
          },
          " ",
          {
            "text": "-",
            "strong": "G2532"
          },
          " ",
          {
            "text": "others [say]",
            "strong": "G243"
          },
          " ",
          {
            "text": "Elijah",
            "strong": "G2243"
          },
          "; ",
          {
            "text": "and still",
            "strong": "G1161"
          },
          " ",
          {
            "text": "others",
            "strong": "G243"
          },
          ", ",
          {
            "text": "-",
            "strong": "G3754"
          },
          " ",
          {
            "text": "one",
            "strong": "G1520"
          },
          " ",
          {
            "text": "of the",
            "strong": "G3588"
          },
          " ",
          {
            "text": "prophets",
            "strong": "G4396"
          },
          ".\u201d"
        ]
      },
      {
        "type": "verse",
        "number": 29,
        "content": [
          "\u201c",
          {
            "text": "But [what about]",
            "strong": "G1161"
          },
          " ",
          {
            "text": "you",
            "strong": "G4771"
          },
          "?\u201d ",
          {
            "text": "-",
            "strong": "G2532"
          },
          " ",
          {
            "text": "[Jesus]",
            "strong": "G846"
          },
          " ",
          {
            "text": "asked",
            "strong": "G1905"
          },
          " ",
          {
            "text": "-",
            "strong": "G846"
          },
          ". \u201c",
          {
            "text": "Who",
            "strong": "G5101"
          },
          " ",
          {
            "text": "do you say",
            "strong": "G3004"
          },
          " ",
          {
            "text": "I",
            "strong": "G1473"
          },
          " ",
          {
            "text": "am",
            "strong": "G1510"
          },
          "?\u201d ",
          {
            "text": "-",
            "strong": "G3588"
          },
          " ",
          {
            "text": "Peter",
            "strong": "G4074"
          },
          " ",
          {
            "text": "answered",
            "strong": "G611"
          },
          " ",
          {
            "text": "-",
            "strong": "G3004"
          },
          " ",
          {
            "text": "-",
            "strong": "G846"
          },
          ", \u201c",
          {
            "text": "You",
            "strong": "G4771"
          },
          " ",
          {
            "text": "are",
            "strong": "G1510"
          },
          " ",
          {
            "text": "the",
            "strong": "G3588"
          },
          " ",
          {
            "text": "Christ",
            "strong": "G5547"
          },
          ".\u201d"
        ]
      },
      {
        "type": "verse",
        "number": 30,
        "content": [
          {
            "text": "And",
            "strong": "G2532"
          },
          " ",
          {
            "text": "[Jesus] warned",
            "strong": "G2008"
          },
          " ",
          {
            "text": "them",
            "strong": "G846"
          },
          " ",
          {
            "text": "-",
            "strong": "G2443"
          },
          " ",
          {
            "text": "not to tell anyone",
            "strong": "G3004"
          },
          {
            "text": ". . .",
            "strong": "G3367"
          },
          " ",
          {
            "text": "about",
            "strong": "G4012"
          },
          " ",
          {
            "text": "Him",
            "strong": "G846"
          },
          "."
        ]
      },
      {
        "type": "verse",
        "number": 31,
        "content": [
          {
            "text": "Then",
            "strong": "G2532"
          },
          " ",
          {
            "text": "He began",
            "strong": "G756"
          },
          " ",
          {
            "text": "to teach",
            "strong": "G1321"
          },
          " ",
          {
            "text": "them",
            "strong": "G846"
          },
          " ",
          {
            "text": "that",
            "strong": "G3754"
          },
          " ",
          {
            "text": "the",
            "strong": "G3588"
          },
          " ",
          {
            "text": "Son",
            "strong": "G5207"
          },
          " ",
          {
            "text": "-",
            "strong": "G3588"
          },
          " ",
          {
            "text": "of Man",
            "strong": "G444"
          },
          " ",
          {
            "text": "must",
            "strong": "G1163"
          },
          " ",
          {
            "text": "suffer",
            "strong": "G3958"
          },
          " ",
          {
            "text": "many things",
            "strong": "G4183"
          },
          " ",
          {
            "text": "and",
            "strong": "G2532"
          },
          " ",
          {
            "text": "be rejected",
            "strong": "G593"
          },
          " ",
          {
            "text": "by",
            "strong": "G5259"
          },
          " ",
          {
            "text": "the",
            "strong": "G3588"
          },
          " ",
          {
            "text": "elders",
            "strong": "G4245"
          },
          ", ",
          {
            "text": "-",
            "strong": "G2532"
          },
          " ",
          {
            "text": "-",
            "strong": "G3588"
          },
          " ",
          {
            "text": "chief priests",
            "strong": "G749"
          },
          ", ",
          {
            "text": "and",
            "strong": "G2532"
          },
          " ",
          {
            "text": "-",
            "strong": "G3588"
          },
          " ",
          {
            "text": "scribes",
            "strong": "G1122"
          },
          ", ",
          {
            "text": "and",
            "strong": "G2532"
          },
          " ",
          {
            "text": "[that] He must be killed",
            "strong": "G615"
          },
          " ",
          {
            "text": "and",
            "strong": "G2532"
          },
          " ",
          {
            "text": "after",
            "strong": "G3326"
          },
          " ",
          {
            "text": "three",
            "strong": "G5140"
          },
          " ",
          {
            "text": "days",
            "strong": "G2250"
          },
          " ",
          {
            "text": "rise [again]",
            "strong": "G450"
          },
          "."
        ]
      },
      {
        "type": "verse",
        "number": 32,
        "content": [
          {
            "text": "-",
            "strong": "G2532"
          },
          " ",
          {
            "text": "He spoke",
            "strong": "G2980"
          },
          " ",
          {
            "text": "[this]",
            "strong": "G3588"
          },
          " ",
          {
            "text": "message",
            "strong": "G3056"
          },
          " ",
          {
            "text": "quite frankly",
            "strong": "G3954"
          },
          ", ",
          {
            "text": "and",
            "strong": "G2532"
          },
          " ",
          {
            "text": "-",
            "strong": "G3588"
          },
          " ",
          {
            "text": "Peter",
            "strong": "G4074"
          },
          " ",
          {
            "text": "took Him aside",
            "strong": "G4355"
          },
          {
            "text": ". . .",
            "strong": "G846"
          },
          " ",
          {
            "text": "[and] began",
            "strong": "G756"
          },
          " ",
          {
            "text": "to rebuke",
            "strong": "G2008"
          },
          " ",
          {
            "text": "Him",
            "strong": "G846"
          },
          "."
        ]
      },
      {
        "type": "verse",
        "number": 33,
        "content": [
          {
            "text": "-",
            "strong": "G3588"
          },
          " ",
          {
            "text": "But [Jesus]",
            "strong": "G1161"
          },
          ", ",
          {
            "text": "turning",
            "strong": "G1994"
          },
          " ",
          {
            "text": "and",
            "strong": "G2532"
          },
          " ",
          {
            "text": "looking at",
            "strong": "G3708"
          },
          " ",
          {
            "text": "His",
            "strong": "G846"
          },
          " ",
          {
            "text": "-",
            "strong": "G3588"
          },
          " ",
          {
            "text": "disciples",
            "strong": "G3101"
          },
          ", ",
          {
            "text": "rebuked",
            "strong": "G2008"
          },
          " ",
          {
            "text": "Peter",
            "strong": "G4074"
          },
          " ",
          {
            "text": "and",
            "strong": "G2532"
          },
          " ",
          {
            "text": "said",
            "strong": "G3004"
          },
          ", \u201c",
          {
            "text": "Get",
            "strong": "G5217"
          },
          " ",
          {
            "text": "behind",
            "strong": "G3694"
          },
          " ",
          {
            "text": "Me",
            "strong": "G1473"
          },
          ", ",
          {
            "text": "Satan",
            "strong": "G4567"
          },
          "! ",
          {
            "text": "For",
            "strong": "G3754"
          },
          " ",
          {
            "text": "vvv",
            "strong": "G3756"
          },
          " ",
          {
            "text": "you do not have in mind",
            "strong": "G5426"
          },
          " ",
          {
            "text": "the",
            "strong": "G3588"
          },
          " ",
          {
            "text": "things",
            "strong": "G3588"
          },
          " ",
          {
            "text": "of God",
            "strong": "G2316"
          },
          ", ",
          {
            "text": "but",
            "strong": "G235"
          },
          " ",
          {
            "text": "the",
            "strong": "G3588"
          },
          " ",
          {
            "text": "things",
            "strong": "G3588"
          },
          " ",
          {
            "text": "of men",
            "strong": "G444"
          },
          ".\u201d"
        ]
      },
      {
        "type": "verse",
        "number": 34,
        "content": [
          {
            "text": "Then",
            "strong": "G2532"
          },
          " ",
          {
            "text": "[Jesus] called",
            "strong": "G4341"
          },
          " ",
          {
            "text": "the",
            "strong": "G3588"
          },
          " ",
          {
            "text": "crowd {to Him}",
            "strong": "G3793"
          },
          " ",
          {
            "text": "along with",
            "strong": "G4862"
          },
          " ",
          {
            "text": "His",
            "strong": "G846"
          },
          " ",
          {
            "text": "-",
            "strong": "G3588"
          },
          " ",
          {
            "text": "disciples",
            "strong": "G3101"
          },
          ", ",
          {
            "text": "[and] He told",
            "strong": "G2036"
          },
          " ",
          {
            "text": "them",
            "strong": "G846"
          },
          ", \u201c",
          {
            "text": "If",
            "strong": "G1487"
          },
          " ",
          {
            "text": "anyone",
            "strong": "G5100"
          },
          " ",
          {
            "text": "wants",
            "strong": "G2309"
          },
          " ",
          {
            "text": "to come",
            "strong": "G2064"
          },
          " ",
          {
            "text": "after",
            "strong": "G3694"
          },
          " ",
          {
            "text": "Me",
            "strong": "G1473"
          },
          ", ",
          {
            "text": "he must deny",
            "strong": "G533"
          },
          " ",
          {
            "text": "himself",
            "strong": "G1438"
          },
          " ",
          {
            "text": "and",
            "strong": "G2532"
          },
          " ",
          {
            "text": "take up",
            "strong": "G142"
          },
          " ",
          {
            "text": "his",
            "strong": "G846"
          },
          " ",
          {
            "text": "-",
            "strong": "G3588"
          },
          " ",
          {
            "text": "cross",
            "strong": "G4716"
          },
          " ",
          {
            "text": "and",
            "strong": "G2532"
          },
          " ",
          {
            "text": "follow",
            "strong": "G190"
          },
          " ",
          {
            "text": "Me",
            "strong": "G1473"
          },
          "."
        ]
      },
      {
        "type": "verse",
        "number": 35,
        "content": [
          {
            "text": "For",
            "strong": "G1063"
          },
          " ",
          {
            "text": "whoever",
            "strong": "G3739"
          },
          " ",
          {
            "text": "vvv",
            "strong": "G1437"
          },
          " ",
          {
            "text": "wants",
            "strong": "G2309"
          },
          " ",
          {
            "text": "to save",
            "strong": "G4982"
          },
          " ",
          {
            "text": "-",
            "strong": "G3588"
          },
          " ",
          {
            "text": "his",
            "strong": "G846"
          },
          " ",
          {
            "text": "life",
            "strong": "G5590"
          },
          " ",
          {
            "text": "will lose",
            "strong": "G622"
          },
          " ",
          {
            "text": "it",
            "strong": "G846"
          },
          ", ",
          {
            "text": "but",
            "strong": "G1161"
          },
          " ",
          {
            "text": "whoever",
            "strong": "G3739"
          },
          {
            "text": ". . .",
            "strong": "G302"
          },
          " ",
          {
            "text": "loses",
            "strong": "G622"
          },
          " ",
          {
            "text": "his",
            "strong": "G846"
          },
          " ",
          {
            "text": "-",
            "strong": "G3588"
          },
          " ",
          {
            "text": "life",
            "strong": "G5590"
          },
          " ",
          {
            "text": "for My sake",
            "strong": "G1752"
          },
          {
            "text": ". . .",
            "strong": "G1473"
          },
          " ",
          {
            "text": "and",
            "strong": "G2532"
          },
          " ",
          {
            "text": "for the",
            "strong": "G3588"
          },
          " ",
          {
            "text": "gospel",
            "strong": "G2098"
          },
          " ",
          {
            "text": "will save",
            "strong": "G4982"
          },
          " ",
          {
            "text": "it",
            "strong": "G846"
          },
          "."
        ]
      },
      {
        "type": "verse",
        "number": 36,
        "content": [
          {
            "text": "-",
            "strong": "G1063"
          },
          " ",
          {
            "text": "What",
            "strong": "G5101"
          },
          " ",
          {
            "text": "does it profit",
            "strong": "G5623"
          },
          " ",
          {
            "text": "a man",
            "strong": "G444"
          },
          " ",
          {
            "text": "to gain",
            "strong": "G2770"
          },
          " ",
          {
            "text": "the",
            "strong": "G3588"
          },
          " ",
          {
            "text": "whole",
            "strong": "G3650"
          },
          " ",
          {
            "text": "world",
            "strong": "G2889"
          },
          ", ",
          {
            "text": "yet",
            "strong": "G2532"
          },
          " ",
          {
            "text": "forfeit",
            "strong": "G2210"
          },
          " ",
          {
            "text": "his",
            "strong": "G846"
          },
          " ",
          {
            "text": "-",
            "strong": "G3588"
          },
          " ",
          {
            "text": "soul",
            "strong": "G5590"
          },
          "?"
        ]
      },
      {
        "type": "verse",
        "number": 37,
        "content": [
          {
            "text": "Or",
            "strong": "G1063"
          },
          " ",
          {
            "text": "what",
            "strong": "G5101"
          },
          " ",
          {
            "text": "{can} a man",
            "strong": "G444"
          },
          " ",
          {
            "text": "give",
            "strong": "G1325"
          },
          " ",
          {
            "text": "in exchange",
            "strong": "G465"
          },
          " ",
          {
            "text": "for",
            "strong": "G3588"
          },
          " ",
          {
            "text": "his",
            "strong": "G846"
          },
          " ",
          {
            "text": "soul",
            "strong": "G5590"
          },
          "?"
        ]
      },
      {
        "type": "verse",
        "number": 38,
        "content": [
          {
            "text": "-",
            "strong": "G1063"
          },
          " ",
          {
            "text": "If anyone",
            "strong": "G3739"
          },
          " ",
          {
            "text": "vvv",
            "strong": "G1437"
          },
          " ",
          {
            "text": "is ashamed of",
            "strong": "G1870"
          },
          " ",
          {
            "text": "Me",
            "strong": "G1473"
          },
          " ",
          {
            "text": "and",
            "strong": "G2532"
          },
          " ",
          {
            "text": "My",
            "strong": "G1699"
          },
          " ",
          {
            "text": "-",
            "strong": "G3588"
          },
          " ",
          {
            "text": "words",
            "strong": "G3056"
          },
          " ",
          {
            "text": "in",
            "strong": "G1722"
          },
          " ",
          {
            "text": "this",
            "strong": "G3778"
          },
          " ",
          {
            "text": "-",
            "strong": "G3588"
          },
          " ",
          {
            "text": "adulterous",
            "strong": "G3428"
          },
          " ",
          {
            "text": "and",
            "strong": "G2532"
          },
          " ",
          {
            "text": "sinful",
            "strong": "G268"
          },
          " ",
          {
            "text": "-",
            "strong": "G3588"
          },
          " ",
          {
            "text": "generation",
            "strong": "G1074"
          },
          ", ",
          {
            "text": "the",
            "strong": "G3588"
          },
          " ",
          {
            "text": "Son",
            "strong": "G5207"
          },
          " ",
          {
            "text": "-",
            "strong": "G3588"
          },
          " ",
          {
            "text": "of Man",
            "strong": "G444"
          },
          " ",
          {
            "text": "vvv",
            "strong": "G2532"
          },
          " ",
          {
            "text": "will also be ashamed of",
            "strong": "G1870"
          },
          " ",
          {
            "text": "him",
            "strong": "G846"
          },
          " ",
          {
            "text": "when",
            "strong": "G3752"
          },
          " ",
          {
            "text": "He comes",
            "strong": "G2064"
          },
          " ",
          {
            "text": "in",
            "strong": "G1722"
          },
          " ",
          {
            "text": "His",
            "strong": "G846"
          },
          " ",
          {
            "text": "-",
            "strong": "G3588"
          },
          " ",
          {
            "text": "Father\u2019s",
            "strong": "G3962"
          },
          " ",
          {
            "text": "-",
            "strong": "G3588"
          },
          " ",
          {
            "text": "glory",
            "strong": "G1391"
          },
          " ",
          {
            "text": "with",
            "strong": "G3326"
          },
          " ",
          {
            "text": "the",
            "strong": "G3588"
          },
          " ",
          {
            "text": "-",
            "strong": "G3588"
          },
          " ",
          {
            "text": "holy",
            "strong": "G40"
          },
          " ",
          {
            "text": "angels",
            "strong": "G32"
          },
          ".\u201d"
        ]
      }
    ],
    "footnotes": []
  }
}