{
  "translation": {
    "id": "BSB",
    "name": "Berean Standard Bible",
    "language": "en",
    "license": "CC0",
    "website": "https://berean.bible"
  },
  "book": {
    "id": "NUM",
    "name": "Numbers",
    "number": 4
  },
  "chapter": {
    "number": 25,
    "content": [
      {
        "type": "verse",
        "number": 1,
        "content": [
          {
            "text": "While Israel",
            "strong": "H3478"
          },
          " ",
          {
            "text": "was staying",
            "strong": "H3427"
          },
          " ",
          {
            "text": "in Shittim",
            "strong": "H7851"
          },
          ", ",
          {
            "text": "the men",
            "strong": "H5971"
          },
          " ",
          {
            "text": "began",
            "strong": "H2490"
          },
          " ",
          {
            "text": "to indulge in sexual immorality",
            "strong": "H2181"
          },
          " ",
          {
            "text": "with",
            "strong": "H413"
          },
          " ",
          {
            "text": "the daughters",
            "strong": "H1323"
          },
          " ",
          {
            "text": "of Moab",
            "strong": "H4124"
          },
          ","
        ]
      },
      {
        "type": "verse",
        "number": 2,
        "content": [
          {
            "text": "who also invited",
            "strong": "H7121"
          },
          " ",
          {
            "text": "them",
            "strong": "H5971"
          },
          " ",
          {
            "text": "to the sacrifices",
            "strong": "H2077"
          },
          " ",
          {
            "text": "for their gods",
            "strong": "H430"
          },
          ". ",
          {
            "text": "And the people",
            "strong": "H5971"
          },
          " ",
          {
            "text": "ate",
            "strong": "H398"
          },
          " ",
          {
            "text": "and bowed down",
            "strong": "H7812"
          },
          " ",
          {
            "text": "to these gods",
            "strong": "H430"
          },
          "."
        ]
      },
      {
        "type": "verse",
        "number": 3,
        "content": [
          {
            "text": "So Israel",
            "strong": "H3478"
          },
          {
            "text": ". . .",
            "strong": "H1187"
          },
          " ",
          {
            "text": "joined in worshiping",
            "strong": "H6775"
          },
          " ",
          {
            "text": "Baal of Peor",
            "strong": "H1187"
          },
          ", ",
          {
            "text": "and the anger",
            "strong": "H639"
          },
          " ",
          {
            "text": "of the LORD",
            "strong": "H3068"
          },
          " ",
          {
            "text": "burned",
            "strong": "H2734"
          },
          " ",
          {
            "text": "against [them]",
            "strong": "H3478"
          },
          "."
        ]
      },
      {
        "type": "verse",
        "number": 4,
        "content": [
          {
            "text": "Then the LORD",
            "strong": "H3068"
          },
          " ",
          {
            "text": "said",
            "strong": "H559"
          },
          " ",
          {
            "text": "to",
            "strong": "H413"
          },
          " ",
          {
            "text": "Moses",
            "strong": "H4872"
          },
          ", \u201c",
          {
            "text": "Take",
            "strong": "H3947"
          },
          " ",
          {
            "text": "-",
            "strong": "H853"
          },
          " ",
          {
            "text": "all",
            "strong": "H3605"
          },
          " ",
          {
            "text": "the leaders",
            "strong": "H7218"
          },
          " ",
          {
            "text": "of the people",
            "strong": "H5971"
          },
          " ",
          {
            "text": "and execute",
            "strong": "H3363"
          },
          " ",
          {
            "text": "them",
            "strong": "H853"
          },
          " ",
          {
            "text": "in",
            "strong": "H5048"
          },
          " ",
          {
            "text": "broad daylight",
            "strong": "H8121"
          },
          " ",
          {
            "text": "before the LORD",
            "strong": "H3068"
          },
          ", ",
          {
            "text": "so that [His]",
            "strong": "H3068"
          },
          " ",
          {
            "text": "fierce",
            "strong": "H2740"
          },
          " ",
          {
            "text": "anger",
            "strong": "H639"
          },
          " ",
          {
            "text": "may turn away",
            "strong": "H7725"
          },
          " ",
          {
            "text": "from Israel",
            "strong": "H3478"
          },
          ".\u201d"
        ]
      },
      {
        "type": "verse",
        "number": 5,
        "content": [
          {
            "text": "So Moses",
            "strong": "H4872"
          },
          {
            "text": ". . .",
            "strong": "H413"
          },
          " ",
          {
            "text": "told",
            "strong": "H559"
          },
          " ",
          {
            "text": "the judges",
            "strong": "H8199"
          },
          " ",
          {
            "text": "of Israel",
            "strong": "H3478"
          },
          ", \u201c",
          {
            "text": "Each of you must kill",
            "strong": "H2026"
          },
          " ",
          {
            "text": "all of his men",
            "strong": "H376"
          },
          {
            "text": ". . .",
            "strong": "H582"
          },
          " ",
          {
            "text": "who have joined in worshiping",
            "strong": "H6775"
          },
          " ",
          {
            "text": "vvv",
            "strong": "H1187"
          },
          " ",
          {
            "text": "Baal of Peor",
            "strong": "H1187"
          },
          ".\u201d"
        ]
      },
      {
        "type": "verse",
        "number": 6,
        "content": [
          {
            "text": "Just then",
            "strong": "H2009"
          },
          " ",
          {
            "text": "an Israelite",
            "strong": "H1121"
          },
          {
            "text": ". . .",
            "strong": "H3478"
          },
          " ",
          {
            "text": "man",
            "strong": "H376"
          },
          " ",
          {
            "text": "vvv",
            "strong": "H935"
          },
          " ",
          {
            "text": "brought",
            "strong": "H7126"
          },
          " ",
          {
            "text": "to",
            "strong": "H413"
          },
          " ",
          {
            "text": "his family",
            "strong": "H251"
          },
          " ",
          {
            "text": "-",
            "strong": "H853"
          },
          " ",
          {
            "text": "a Midianite woman",
            "strong": "H4084"
          },
          " ",
          {
            "text": "in the sight",
            "strong": "H5869"
          },
          " ",
          {
            "text": "of Moses",
            "strong": "H4872"
          },
          " ",
          {
            "text": "[and]",
            "strong": "H5869"
          },
          " ",
          {
            "text": "the whole",
            "strong": "H3605"
          },
          " ",
          {
            "text": "congregation",
            "strong": "H5712"
          },
          {
            "text": ". . .",
            "strong": "H1121"
          },
          " ",
          {
            "text": "of Israel",
            "strong": "H3478"
          },
          " ",
          {
            "text": "while they",
            "strong": "H1992"
          },
          " ",
          {
            "text": "were weeping",
            "strong": "H1058"
          },
          " ",
          {
            "text": "at the entrance",
            "strong": "H6607"
          },
          " ",
          {
            "text": "to the Tent",
            "strong": "H168"
          },
          " ",
          {
            "text": "of Meeting",
            "strong": "H4150"
          },
          "."
        ]
      },
      {
        "type": "verse",
        "number": 7,
        "content": [
          {
            "text": "On seeing this",
            "strong": "H7200"
          },
          ", ",
          {
            "text": "Phinehas",
            "strong": "H6372"
          },
          " ",
          {
            "text": "son",
            "strong": "H1121"
          },
          " ",
          {
            "text": "of Eleazar",
            "strong": "H499"
          },
          ", ",
          {
            "text": "the son",
            "strong": "H1121"
          },
          " ",
          {
            "text": "of Aaron",
            "strong": "H175"
          },
          " ",
          {
            "text": "the priest",
            "strong": "H3548"
          },
          ", ",
          {
            "text": "got up",
            "strong": "H6965"
          },
          " ",
          {
            "text": "from",
            "strong": "H8432"
          },
          " ",
          {
            "text": "the assembly",
            "strong": "H5712"
          },
          ", ",
          {
            "text": "took",
            "strong": "H3947"
          },
          " ",
          {
            "text": "a spear",
            "strong": "H7420"
          },
          " ",
          {
            "text": "in his hand",
            "strong": "H3027"
          },
          ","
        ]
      },
      {
        "type": "verse",
        "number": 8,
        "content": [
          {
            "text": "followed",
            "strong": "H935"
          },
          {
            "text": ". . .",
            "strong": "H310"
          },
          " ",
          {
            "text": "the Israelite",
            "strong": "H3478"
          },
          {
            "text": ". . .",
            "strong": "H376"
          },
          " ",
          {
            "text": "into",
            "strong": "H413"
          },
          " ",
          {
            "text": "the tent",
            "strong": "H6898"
          },
          ", ",
          {
            "text": "and drove [the spear] through",
            "strong": "H1856"
          },
          " ",
          {
            "text": "-",
            "strong": "H853"
          },
          " ",
          {
            "text": "both of them",
            "strong": "H8147"
          },
          "\u2014 ",
          {
            "text": "-",
            "strong": "H853"
          },
          " ",
          {
            "text": "vvv",
            "strong": "H376"
          },
          " ",
          {
            "text": "through the Israelite",
            "strong": "H3478"
          },
          " ",
          {
            "text": "-",
            "strong": "H853"
          },
          " ",
          {
            "text": "and on through",
            "strong": "H413"
          },
          " ",
          {
            "text": "the belly",
            "strong": "H6897"
          },
          " ",
          {
            "text": "of the woman",
            "strong": "H802"
          },
          ". ",
          {
            "text": "So the plague",
            "strong": "H4046"
          },
          " ",
          {
            "text": "against",
            "strong": "H5921"
          },
          " ",
          {
            "text": "the Israelites",
            "strong": "H1121"
          },
          {
            "text": ". . .",
            "strong": "H3478"
          },
          " ",
          {
            "text": "was halted",
            "strong": "H6113"
          },
          ","
        ]
      },
      {
        "type": "verse",
        "number": 9,
        "content": [
          {
            "text": "-",
            "strong": "H1961"
          },
          " ",
          {
            "text": "but those who died",
            "strong": "H4191"
          },
          " ",
          {
            "text": "in the plague",
            "strong": "H4046"
          },
          " ",
          {
            "text": "numbered 24,000",
            "strong": "H702"
          },
          {
            "text": ". . .",
            "strong": "H6242"
          },
          {
            "text": ". . .",
            "strong": "H505"
          },
          "."
        ]
      },
      {
        "type": "verse",
        "number": 10,
        "content": [
          {
            "text": "Then the LORD",
            "strong": "H3068"
          },
          " ",
          {
            "text": "said",
            "strong": "H1696"
          },
          " ",
          {
            "text": "to",
            "strong": "H413"
          },
          " ",
          {
            "text": "Moses",
            "strong": "H4872"
          },
          {
            "text": ". . .",
            "strong": "H559"
          },
          ","
        ]
      },
      {
        "type": "verse",
        "number": 11,
        "content": [
          "\u201c",
          {
            "text": "Phinehas",
            "strong": "H6372"
          },
          " ",
          {
            "text": "son",
            "strong": "H1121"
          },
          " ",
          {
            "text": "of Eleazar",
            "strong": "H499"
          },
          ", ",
          {
            "text": "the son",
            "strong": "H1121"
          },
          " ",
          {
            "text": "of Aaron",
            "strong": "H175"
          },
          " ",
          {
            "text": "the priest",
            "strong": "H3548"
          },
          ", ",
          {
            "text": "has turned",
            "strong": "H7725"
          },
          " ",
          {
            "text": "-",
            "strong": "H853"
          },
          " ",
          {
            "text": "My wrath",
            "strong": "H2534"
          },
          " ",
          {
            "text": "away from",
            "strong": "H5921"
          },
          " ",
          {
            "text": "the Israelites",
            "strong": "H1121"
          },
          {
            "text": ". . .",
            "strong": "H3478"
          },
          "; ",
          {
            "text": "for he was zealous",
            "strong": "H7065"
          },
          " ",
          {
            "text": "[for My sake]",
            "strong": "H7068"
          },
          " ",
          {
            "text": "among them",
            "strong": "H8432"
          },
          ", ",
          {
            "text": "-",
            "strong": "H853"
          },
          " ",
          {
            "text": "so that I did not",
            "strong": "H3808"
          },
          " ",
          {
            "text": "consume",
            "strong": "H3615"
          },
          " ",
          {
            "text": "-",
            "strong": "H853"
          },
          " ",
          {
            "text": "the Israelites",
            "strong": "H1121"
          },
          {
            "text": ". . .",
            "strong": "H3478"
          },
          " ",
          {
            "text": "in My zeal",
            "strong": "H7068"
          },
          "."
        ]
      },
      {
        "type": "verse",
        "number": 12,
        "content": [
          {
            "text": "Declare",
            "strong": "H559"
          },
          ", ",
          {
            "text": "therefore",
            "strong": "H3651"
          },
          ", ",
          {
            "text": "that",
            "strong": "H2005"
          },
          " ",
          {
            "text": "I am granting",
            "strong": "H5414"
          },
          " him ",
          {
            "text": "-",
            "strong": "H853"
          },
          " ",
          {
            "text": "My covenant",
            "strong": "H1285"
          },
          " ",
          {
            "text": "of peace",
            "strong": "H7965"
          },
          "."
        ]
      },
      {
        "type": "verse",
        "number": 13,
        "content": [
          {
            "text": "It will be",
            "strong": "H1961"
          },
          " ",
          {
            "text": "a covenant",
            "strong": "H1285"
          },
          " ",
          {
            "text": "of permanent",
            "strong": "H5769"
          },
          " ",
          {
            "text": "priesthood",
            "strong": "H3550"
          },
          " for him ",
          {
            "text": "vvv",
            "strong": "H310"
          },
          " ",
          {
            "text": "and his descendants",
            "strong": "H2233"
          },
          ", ",
          {
            "text": "because",
            "strong": "H8478"
          },
          " ",
          {
            "text": "-",
            "strong": "H834"
          },
          " ",
          {
            "text": "he was zealous",
            "strong": "H7065"
          },
          " ",
          {
            "text": "for his God",
            "strong": "H430"
          },
          " ",
          {
            "text": "and made atonement",
            "strong": "H3722"
          },
          " ",
          {
            "text": "for",
            "strong": "H5921"
          },
          " ",
          {
            "text": "the Israelites",
            "strong": "H1121"
          },
          {
            "text": ". . .",
            "strong": "H3478"
          },
          ".\u201d"
        ]
      },
      {
        "type": "verse",
        "number": 14,
        "content": [
          {
            "text": "The name",
            "strong": "H8034"
          },
          " ",
          {
            "text": "vvv",
            "strong": "H376"
          },
          " ",
          {
            "text": "of the Israelite",
            "strong": "H3478"
          },
          " ",
          {
            "text": "who was slain",
            "strong": "H5221"
          },
          " ",
          {
            "text": "-",
            "strong": "H834"
          },
          " ",
          {
            "text": "-",
            "strong": "H5221"
          },
          " ",
          {
            "text": "with",
            "strong": "H854"
          },
          " ",
          {
            "text": "the Midianite woman",
            "strong": "H4084"
          },
          " ",
          {
            "text": "was Zimri",
            "strong": "H2174"
          },
          " ",
          {
            "text": "son",
            "strong": "H1121"
          },
          " ",
          {
            "text": "of Salu",
            "strong": "H5543"
          },
          ", ",
          {
            "text": "the leader",
            "strong": "H5387"
          },
          " ",
          {
            "text": "of a Simeonite",
            "strong": "H8099"
          },
          " ",
          {
            "text": "family",
            "strong": "H1"
          },
          {
            "text": ". . .",
            "strong": "H1004"
          },
          "."
        ]
      },
      {
        "type": "verse",
        "number": 15,
        "content": [
          {
            "text": "And the name",
            "strong": "H8034"
          },
          " ",
          {
            "text": "of the slain",
            "strong": "H5221"
          },
          " ",
          {
            "text": "Midianite",
            "strong": "H4084"
          },
          " ",
          {
            "text": "woman",
            "strong": "H802"
          },
          " ",
          {
            "text": "was Cozbi",
            "strong": "H3579"
          },
          ", ",
          {
            "text": "the daughter",
            "strong": "H1323"
          },
          " ",
          {
            "text": "of Zur",
            "strong": "H6698"
          },
          ", ",
          {
            "text": "a tribal",
            "strong": "H523"
          },
          " ",
          {
            "text": "chief",
            "strong": "H7218"
          },
          " ",
          {
            "text": "of a Midianite",
            "strong": "H4080"
          },
          {
            "text": ". . .",
            "strong": "H1931"
          },
          " ",
          {
            "text": "family",
            "strong": "H1"
          },
          {
            "text": ". . .",
            "strong": "H1004"
          },
          "."
        ]
      },
      {
        "type": "verse",
        "number": 16,
        "content": [
          {
            "text": "And the LORD",
            "strong": "H3068"
          },
          {
            "text": ". . .",
            "strong": "H413"
          },
          " ",
          {
            "text": "said",
            "strong": "H1696"
          },
          " ",
          {
            "text": "to Moses",
            "strong": "H4872"
          },
          {
            "text": ". . .",
            "strong": "H559"
          },
          ","
        ]
      },
      {
        "type": "verse",
        "number": 17,
        "content": [
          "\u201c",
          {
            "text": "Attack",
            "strong": "H6887"
          },
          " ",
          {
            "text": "-",
            "strong": "H853"
          },
          " ",
          {
            "text": "the Midianites",
            "strong": "H4084"
          },
          " ",
          {
            "text": "and strike them dead",
            "strong": "H5221"
          },
          " ",
          {
            "text": "-",
            "strong": "H853"
          },
          "."
        ]
      },
      {
        "type": "verse",
        "number": 18,
        "content": [
          {
            "text": "For",
            "strong": "H3588"
          },
          " ",
          {
            "text": "they",
            "strong": "H1992"
          },
          " ",
          {
            "text": "assailed",
            "strong": "H6887"
          },
          " you ",
          {
            "text": "deceitfully",
            "strong": "H5231"
          },
          " ",
          {
            "text": "when",
            "strong": "H834"
          },
          " ",
          {
            "text": "they seduced",
            "strong": "H5230"
          },
          " you ",
          {
            "text": "in",
            "strong": "H5921"
          },
          " ",
          {
            "text": "the matter",
            "strong": "H1697"
          },
          " ",
          {
            "text": "of Peor",
            "strong": "H6465"
          },
          " ",
          {
            "text": "and",
            "strong": "H5921"
          },
          " ",
          {
            "text": "-",
            "strong": "H1697"
          },
          " ",
          {
            "text": "their sister",
            "strong": "H269"
          },
          " ",
          {
            "text": "Cozbi",
            "strong": "H3579"
          },
          ", ",
          {
            "text": "the daughter",
            "strong": "H1323"
          },
          " ",
          {
            "text": "of the Midianite",
            "strong": "H4080"
          },
          " ",
          {
            "text": "leader",
            "strong": "H5387"
          },
          ", ",
          {
            "text": "[the woman] who was killed",
            "strong": "H5221"
          },
          " ",
          {
            "text": "on the day",
            "strong": "H3117"
          },
          " ",
          {
            "text": "the plague",
            "strong": "H4046"
          },
          " ",
          {
            "text": "came",
            "strong": "H5921"
          },
          " ",
          {
            "text": "because of",
            "strong": "H1697"
          },
          " ",
          {
            "text": "Peor",
            "strong": "H6465"
          },
          ".\u201d"
        ]
      }
    ],
    "footnotes": []
  }
}